mmedit/__init__.py
mmedit/version.py
mmedit/.mim/model-index.yml
mmedit/.mim/configs/inpainting/AOT-GAN/AOT-GAN_512x512_4x12_places.py
mmedit/.mim/configs/inpainting/AOT-GAN/metafile.yml
mmedit/.mim/configs/inpainting/deepfillv1/deepfillv1_256x256_4x4_celeba.py
mmedit/.mim/configs/inpainting/deepfillv1/deepfillv1_256x256_8x2_places.py
mmedit/.mim/configs/inpainting/deepfillv1/metafile.yml
mmedit/.mim/configs/inpainting/deepfillv2/deepfillv2_256x256_8x2_celeba.py
mmedit/.mim/configs/inpainting/deepfillv2/deepfillv2_256x256_8x2_places.py
mmedit/.mim/configs/inpainting/deepfillv2/metafile.yml
mmedit/.mim/configs/inpainting/global_local/gl_256x256_8x12_celeba.py
mmedit/.mim/configs/inpainting/global_local/gl_256x256_8x12_places.py
mmedit/.mim/configs/inpainting/global_local/metafile.yml
mmedit/.mim/configs/inpainting/partial_conv/metafile.yml
mmedit/.mim/configs/inpainting/partial_conv/pconv_256x256_stage1_8x1_celeba.py
mmedit/.mim/configs/inpainting/partial_conv/pconv_256x256_stage1_8x1_places.py
mmedit/.mim/configs/inpainting/partial_conv/pconv_256x256_stage2_4x2_celeba.py
mmedit/.mim/configs/inpainting/partial_conv/pconv_256x256_stage2_4x2_places.py
mmedit/.mim/configs/mattors/dim/dim_stage1_v16_1x1_1000k_comp1k.py
mmedit/.mim/configs/mattors/dim/dim_stage2_v16_pln_1x1_1000k_comp1k.py
mmedit/.mim/configs/mattors/dim/dim_stage3_v16_pln_1x1_1000k_comp1k.py
mmedit/.mim/configs/mattors/dim/metafile.yml
mmedit/.mim/configs/mattors/gca/baseline_dimaug_r34_4x10_200k_comp1k.py
mmedit/.mim/configs/mattors/gca/baseline_r34_4x10_200k_comp1k.py
mmedit/.mim/configs/mattors/gca/gca_dimaug_r34_4x10_200k_comp1k.py
mmedit/.mim/configs/mattors/gca/gca_r34_4x10_200k_comp1k.py
mmedit/.mim/configs/mattors/gca/metafile.yml
mmedit/.mim/configs/mattors/indexnet/indexnet_dimaug_mobv2_1x16_78k_comp1k.py
mmedit/.mim/configs/mattors/indexnet/indexnet_mobv2_1x16_78k_comp1k.py
mmedit/.mim/configs/mattors/indexnet/metafile.yml
mmedit/.mim/configs/restorers/basicvsr/basicvsr_reds4.py
mmedit-0.16.1.dist-info/LICENSE
mmedit-0.16.1.dist-info/METADATA
mmedit-0.16.1.dist-info/WHEEL
mmedit-0.16.1.dist-info/top_level.txt
mmedit-0.16.1.dist-info/RECORD
