Metadata-Version: 2.1
Name: mmedit
Version: 0.16.1
Summary: OpenMMLab Image and Video Editing Toolbox and Benchmark
Home-page: https://github.com/open-mmlab/mmediting
Maintainer: MMEditing Contributors
Maintainer-email: openmmlab@gmail.com
License: Apache License 2.0
Keywords: computer vision,super resolution,video interpolation,inpainting,matting,SISR,RefSR,VSR,GAN,VFI
Platform: UNKNOWN
Classifier: Development Status :: 4 - Beta
Classifier: Intended Audience :: Developers
Classifier: Intended Audience :: Education
Classifier: Intended Audience :: Science/Research
Classifier: License :: OSI Approved :: Apache Software License
Classifier: Operating System :: OS Independent
Classifier: Programming Language :: Python :: 3
Classifier: Programming Language :: Python :: 3.7
Classifier: Programming Language :: Python :: 3.8
Classifier: Programming Language :: Python :: 3.9
Classifier: Programming Language :: Python :: 3.10
Classifier: Topic :: Scientific/Engineering :: Artificial Intelligence
Classifier: Topic :: Scientific/Engineering :: Image Processing
Requires-Dist: av
Requires-Dist: facexlib
Requires-Dist: lmdb
Requires-Dist: mmcv-full (>=1.3.13)
Requires-Dist: numpy
Requires-Dist: opencv-python (!=4.5.5.62,!=4.5.5.64)
Requires-Dist: Pillow
Requires-Dist: tensorboard
Requires-Dist: torch
Requires-Dist: torchvision
Requires-Dist: av (==8.0.3) ; python_version < "3.7"
Provides-Extra: all
Requires-Dist: av ; extra == 'all'
Requires-Dist: facexlib ; extra == 'all'
Requires-Dist: lmdb ; extra == 'all'
Requires-Dist: mmcv-full (>=1.3.13) ; extra == 'all'
Requires-Dist: numpy ; extra == 'all'
Requires-Dist: opencv-python (!=4.5.5.62,!=4.5.5.64) ; extra == 'all'
Requires-Dist: Pillow ; extra == 'all'
Requires-Dist: tensorboard ; extra == 'all'
Requires-Dist: torch ; extra == 'all'
Requires-Dist: torchvision ; extra == 'all'
Requires-Dist: codecov ; extra == 'all'
Requires-Dist: flake8 ; extra == 'all'
Requires-Dist: interrogate ; extra == 'all'
Requires-Dist: isort (==5.10.1) ; extra == 'all'
Requires-Dist: onnxruntime ; extra == 'all'
Requires-Dist: pytest ; extra == 'all'
Requires-Dist: pytest-runner ; extra == 'all'
Requires-Dist: yapf ; extra == 'all'
Requires-Dist: av (==8.0.3) ; (python_version < "3.7") and extra == 'all'
Provides-Extra: mim
Requires-Dist: mmcv-full (>=1.3.17) ; extra == 'mim'
Provides-Extra: tests
Requires-Dist: codecov ; extra == 'tests'
Requires-Dist: flake8 ; extra == 'tests'
Requires-Dist: interrogate ; extra == 'tests'
Requires-Dist: isort (==5.10.1) ; extra == 'tests'
Requires-Dist: onnxruntime ; extra == 'tests'
Requires-Dist: pytest ; extra == 'tests'
Requires-Dist: pytest-runner ; extra == 'tests'
Requires-Dist: yapf ; extra == 'tests'
